langchain_prompty/__init__.py
langchain_prompty/core.py
langchain_prompty/langchain.py
langchain_prompty/parsers.py
langchain_prompty/renderers.py
langchain_prompty/utils.py
gigachain_prompty-0.0.2.dist-info/LICENSE
gigachain_prompty-0.0.2.dist-info/METADATA
gigachain_prompty-0.0.2.dist-info/WHEEL
gigachain_prompty-0.0.2.dist-info/RECORD
