Metadata-Version: 2.1
Name: gigachain-prompty
Version: 0.0.2
Summary: An integration package connecting Prompty and GigaChain
Home-page: https://github.com/ai-forever/gigachain
License: MIT
Requires-Python: >=3.8.1,<4.0
Classifier: License :: OSI Approved :: MIT License
Classifier: Programming Language :: Python :: 3
Classifier: Programming Language :: Python :: 3.9
Classifier: Programming Language :: Python :: 3.10
Classifier: Programming Language :: Python :: 3.11
Classifier: Programming Language :: Python :: 3.12
Requires-Dist: gigachain-core (>=0.1.52,<0.3)
Requires-Dist: pyyaml (>=6.0.1,<7.0.0)
Requires-Dist: types-pyyaml (>=6.0.12.20240311,<7.0.0.0)
Project-URL: Repository, https://github.com/ai-forever/gigachain
Project-URL: Source Code, https://github.com/ai-forever/gigachain/tree/master/libs/partners/prompty
